brainglobe/__init__.py
brainglobe-1.3.1.dist-info/LICENSE
brainglobe-1.3.1.dist-info/METADATA
brainglobe-1.3.1.dist-info/WHEEL
brainglobe-1.3.1.dist-info/top_level.txt
brainglobe-1.3.1.dist-info/RECORD
