Metadata-Version: 2.1
Name: brainglobe
Version: 1.3.1
Summary: Python-based tools for computational neuroanatomy.
Author-email: BrainGlobe Developers <hello@brainglobe.info>
License: BSD-3-Clause
Project-URL: homepage, https://brainglobe.info
Project-URL: bug_tracker, https://github.com/brainglobe/brainglobe-meta/issues
Project-URL: documentation, https://docs.brainglobe.info
Project-URL: source_code, https://github.com/brainglobe/brainglobe-meta
Project-URL: user_support, https://forum.image.sc/tag/brainglobe
Project-URL: twitter, https://twitter.com/brain_globe
Classifier: Development Status :: 2 - Pre-Alpha
Classifier: Programming Language :: Python
Classifier: Programming Language :: Python :: 3
Classifier: Programming Language :: Python :: 3.10
Classifier: Programming Language :: Python :: 3.11
Classifier: Programming Language :: Python :: 3.12
Classifier: Operating System :: OS Independent
Classifier: License :: OSI Approved :: BSD License
Requires-Python: >=3.10.0
License-File: LICENSE
Requires-Dist: brainglobe-atlasapi<3,>=2.0.7
Requires-Dist: brainglobe-heatmap<1,>=0.5.3
Requires-Dist: brainglobe-napari-io<1,>=0.3.4
Requires-Dist: brainglobe-segmentation<2,>=1.2.5
Requires-Dist: brainglobe-space<2,>=1.0.2
Requires-Dist: brainglobe-utils<1,>=0.6.0
Requires-Dist: brainreg[napari]<2,>=1.0.10
Requires-Dist: brainrender-napari<1,>=0.0.3
Requires-Dist: brainrender<3,>=2.1.10
Requires-Dist: cellfinder[napari]<2,>=1.3.2
Requires-Dist: napari[all]
Requires-Dist: brainrender-napari<2,>=0.0.4
Provides-Extra: dev
Requires-Dist: pytest; extra == "dev"
Requires-Dist: pytest-cov; extra == "dev"
Requires-Dist: coverage; extra == "dev"
Requires-Dist: tox; extra == "dev"
Requires-Dist: black; extra == "dev"
Requires-Dist: mypy; extra == "dev"
Requires-Dist: pre-commit; extra == "dev"
Requires-Dist: ruff; extra == "dev"
Requires-Dist: setuptools-scm; extra == "dev"
